dataframer/__init__.py
dataframer/_base_client.py
dataframer/_client.py
dataframer/_compat.py
dataframer/_constants.py
dataframer/_exceptions.py
dataframer/_files.py
dataframer/_models.py
dataframer/_qs.py
dataframer/_resource.py
dataframer/_response.py
dataframer/_streaming.py
dataframer/_types.py
dataframer/_version.py
dataframer/py.typed
dataframer/_utils/__init__.py
dataframer/_utils/_compat.py
dataframer/_utils/_datetime_parse.py
dataframer/_utils/_logs.py
dataframer/_utils/_proxy.py
dataframer/_utils/_reflection.py
dataframer/_utils/_resources_proxy.py
dataframer/_utils/_streams.py
dataframer/_utils/_sync.py
dataframer/_utils/_transform.py
dataframer/_utils/_typing.py
dataframer/_utils/_utils.py
dataframer/lib/.keep
dataframer/resources/__init__.py
dataframer/resources/dataframer/__init__.py
dataframer/resources/dataframer/analyze.py
dataframer/resources/dataframer/chat.py
dataframer/resources/dataframer/dataframer.py
dataframer/resources/dataframer/datasets.py
dataframer/resources/dataframer/files.py
dataframer/resources/dataframer/generate.py
dataframer/resources/dataframer/human_labels.py
dataframer/resources/dataframer/red_team.py
dataframer/resources/dataframer/red_team_runs.py
dataframer/resources/dataframer/red_team_specs.py
dataframer/resources/dataframer/evaluations/__init__.py
dataframer/resources/dataframer/evaluations/chat.py
dataframer/resources/dataframer/evaluations/evaluations.py
dataframer/resources/dataframer/runs/__init__.py
dataframer/resources/dataframer/runs/evaluations.py
dataframer/resources/dataframer/runs/generated_files.py
dataframer/resources/dataframer/runs/human_labels.py
dataframer/resources/dataframer/runs/runs.py
dataframer/resources/dataframer/runs/samples.py
dataframer/resources/dataframer/specs/__init__.py
dataframer/resources/dataframer/specs/specs.py
dataframer/resources/dataframer/specs/versions.py
dataframer/types/__init__.py
dataframer/types/dataframer_check_health_response.py
pydataframer-0.3.1.dist-info/METADATA
pydataframer-0.3.1.dist-info/WHEEL
pydataframer-0.3.1.dist-info/licenses/LICENSE
pydataframer-0.3.1.dist-info/RECORD
